llama_index/packs/zenguard/__init__.py
llama_index/packs/zenguard/base.py
llama_index_packs_zenguard-0.4.1.dist-info/METADATA
llama_index_packs_zenguard-0.4.1.dist-info/WHEEL
llama_index_packs_zenguard-0.4.1.dist-info/licenses/LICENSE
llama_index_packs_zenguard-0.4.1.dist-info/RECORD
