Metadata-Version: 2.4
Name: llama-index-packs-zenguard
Version: 0.4.1
Summary: llama-index packs zenguard integration
Author-email: ZenGuard Team <hello@zenguard.ai>
License-Expression: MIT
License-File: LICENSE
Keywords: detector,guard,guardrails,llm security,prompt injection,security,zenguard
Requires-Python: <4.0,>=3.9
Requires-Dist: llama-index-core<0.15,>=0.13.0
Requires-Dist: zenguard<0.3,>=0.2.1
